<?xml version="1.0" encoding="utf-8" ?>
<Defs>

  <TerrainDef ParentName="TileStoneBase">
    <defName>TileBloodstone</defName>
    <label>bloodstone tile</label>
    <color>(120,7,7)</color>
    <costList>
      <Bloodstone>4</Bloodstone>
    </costList>
  </TerrainDef>

  <TerrainDef ParentName="FloorBase">
    <defName>BloodcreteFloor</defName>
    <label>bloodcrete</label>
    <description>Bloodcrete. It is cheap and quick to build, and not bad to look at.</description>
    <texturePath>Terrain/Surfaces/Concrete</texturePath>
    <edgeType>Hard</edgeType>
    <renderPrecedence>70</renderPrecedence>
    <color>(47,0,0)</color>
    <statBases>
      <Beauty>1</Beauty>
      <WorkToBuild>100</WorkToBuild>
    </statBases>
    <costList>
      <Bloodcrete>1</Bloodcrete>
    </costList>
    <designationHotKey>Misc6</designationHotKey>
    <researchPrerequisites>
      <li>Stonecutting</li>
    </researchPrerequisites>
  </TerrainDef>

  <TerrainDef ParentName="FlagstoneBase">
    <defName>FlagstoneBloodstone</defName>
    <label>bloodstone flagstone</label>
    <color>(120,7,7)</color>
    <costList>
      <Bloodstone>4</Bloodstone>
    </costList>
  </TerrainDef>

</Defs>