<?xml version="1.0" encoding="utf-8"?>
<Defs>
	<!-- copied from NegativeEvent, the default, but you can change it however you like 
		you will need to recompile the DLL if you change the DefName -->
	<LetterDef>
		<defName>RH_Letter_GhostsFriendly</defName>
	<color>(120, 176, 216)</color>
    <flashColor>(106, 179, 231)</flashColor>
    <flashInterval>90</flashInterval>
    <arriveSound>LetterArrive_Good</arriveSound>
	</LetterDef>
	
	<LetterDef>
		<defName>RH_Letter_OneFourOneFriendly</defName>
    <color>(120, 176, 216)</color>
    <flashColor>(106, 179, 231)</flashColor>
    <flashInterval>90</flashInterval>
    <arriveSound>LetterArrive_Good</arriveSound>
	</LetterDef>
  
</Defs>