<?xml version="1.0" encoding="utf-8" ?>
<Defs>

<!--============== Manual ==============-->

<ResearchProjectDef>
    <defName>JDSBarrmowArmor</defName>
    <label>Barrow Brothers Armor set</label>
    <description>...</description>
<baseCost>4500</baseCost>
<tab>JDSTheForgetab</tab>
<techLevel>Medieval</techLevel>
<researchViewY>1</researchViewY> <!-- up and down-->
<researchViewX>1</researchViewX> <!-- left and right -->
		<prerequisites>
			<li>JDSTheForgeKnows</li>
		</prerequisites>
</ResearchProjectDef>

</Defs>