<?xml version="1.0" encoding="utf-8"?>

<Patch>

	<!-- Dubs Bad Hygiene -->
	
	<Operation Class="PatchOperationFindMod">
		
    	<mods>
        	<li>Dubs Bad Hygiene</li>
    	</mods>
		
    	<match Class="PatchOperationSequence">
        <success>Always</success>
        <operations>
			
			<!-- Advanced Toilet -->
			
			<li Class="PatchOperationReplace">
				<xpath>/Defs/ThingDef[defName = "ToiletAdv"]/comps/li[@Class = "CompProperties_Power"]/basePowerConsumption</xpath>
				<value>
					<basePowerConsumption>25</basePowerConsumption>
				</value>
			</li>
			
			<!-- Advanced Shower -->
			
			<li Class="PatchOperationReplace">
				<xpath>/Defs/ThingDef[defName = "ShowerAdvStuff"]/comps/li[@Class = "CompProperties_Power"]/basePowerConsumption</xpath>
				<value>
					<basePowerConsumption>25</basePowerConsumption>
				</value>
			</li>
			
        </operations>
    	</match>
	
	</Operation>

</Patch>