<?xml version="1.0" encoding="utf-8"?>
<LanguageData>
	<MultiFloors>Multi-Floors</MultiFloors>
	
	<!-- settings -->
	<MF_Settings_General>General</MF_Settings_General>
	<MF_UseUpperLevelRenderer>Use top view renderer on upper levels (Restart required)</MF_UseUpperLevelRenderer>
	<MF_UseUpperLevelRendererTooltip>Render from top to bottom on upper levels that you can see things on lower levels. Dynamic things and pawns are not visible.</MF_UseUpperLevelRendererTooltip>
	<MF_BlurringLowerLevels>Blur lower levels (Restart required)</MF_BlurringLowerLevels>
	<MF_BlurringLowerLevelsTooltip>Add blurring effects to lower levels when rendering upper levels.</MF_BlurringLowerLevelsTooltip>
	<MF_FixedCameraVerticalTransition>Fixed camera vertical transition</MF_FixedCameraVerticalTransition>
	<MF_FixedCameraVerticalTransitionTooltip>Hotkeys will switch levels with current camera position and zoom size.</MF_FixedCameraVerticalTransitionTooltip>
	<MF_SortMapByLevelInColonistBar>Sort maps by level in colonist bar (Restart required)</MF_SortMapByLevelInColonistBar>
	<MF_AllowsGatheringsOnOtherLevels>Allow gatherings on other levels (Restart required)</MF_AllowsGatheringsOnOtherLevels>
	<MF_AllowsGatheringsOnOtherLevelsTooltip>When turned off, gatherings like party and concert will only happen on the ground.</MF_AllowsGatheringsOnOtherLevelsTooltip>
	
	<MF_Settings_MapGen>Map Generation</MF_Settings_MapGen>
	<MF_GenerateRocksOnUpperLevels>Generate rocks on upper levels</MF_GenerateRocksOnUpperLevels>
	<MF_GenerateRocksOnUpperLevelsTooltip>Generate random rocks for mountain to simulate hill continuation. Might increase the loading time of your save.</MF_GenerateRocksOnUpperLevelsTooltip>
	<MF_GenerateBasementWithoutCaves>Flood fill whole map on upper levels</MF_GenerateBasementWithoutCaves>
	<MF_GenerateBasementWithoutCavesTooltip>Upper floors are built on top of the roofs of the lower levels. To avoid freezing the game in mountainous biomes, expansion is limited to a maximum of 9 sections (17×17 cells) centered around the staircase.</MF_GenerateBasementWithoutCavesTooltip>
	<MF_GenerateBasementWithoutCaves>Generate basement without caves</MF_GenerateBasementWithoutCaves>
	<MF_GenerateBasementWithoutCavesTooltip>When enabled, basements will only generate with rocks and possible ores.</MF_GenerateBasementWithoutCavesTooltip>
	
	<MF_Settings_Needs>Needs</MF_Settings_Needs>
	<MF_SetLivingLevelWhenAssigningBed>Set living level when assigning bed</MF_SetLivingLevelWhenAssigningBed>
	<MF_SetOtherLevelWhenAssigningBed>Also set joy and diet level when assigning bed</MF_SetOtherLevelWhenAssigningBed>
	<MF_RedirectIntervalDesc>Pawns would be redirected to their living/diet/joy level when their need is low. If they move to other levels, don't redirect them immediately.</MF_RedirectIntervalDesc>
	<MF_RedirectInterval>Redirect interval:</MF_RedirectInterval>
	
	<MF_Settings_Stairs>Stairs</MF_Settings_Stairs>
	<MF_FlipStairDestinationCell>Flip stair destination cell</MF_FlipStairDestinationCell>
	<MF_FlipStairDestinationCellTooltip>Stairs are designed as Z shape. If you have retexture mod that flips it, you can turn this on to spawn pawns on the correct destination.</MF_FlipStairDestinationCellTooltip>
	<MF_MinRoomSizeForStairs>Min room size for stairs</MF_MinRoomSizeForStairs>
	<MF_SwitchLevelWaitTick>Wait tick switching between levels</MF_SwitchLevelWaitTick>
	<MF_HeatExchangeEfficiencyDesc>Heat would be exchanged through stairs. Configure how fast they should synchronize between two rooms.</MF_HeatExchangeEfficiencyDesc>
	<MF_HeatExchangeEfficiency>Heat exchange efficiency: </MF_HeatExchangeEfficiency>
	<MF_ExchangeIntervalMultiplierDesc>Power, heat, gas will be exchanged between levels on a regular basis. But you can make it rarer.</MF_ExchangeIntervalMultiplierDesc>
	<MF_ExchangeIntervalMultiplier>Exchange interval multiplier: {0}</MF_ExchangeIntervalMultiplier>
	<MF_AutoTransferIntervalMultiplierDesc>Transfer "orders" will also be added periodically once you set them in Transfer tab of stairs.</MF_AutoTransferIntervalMultiplierDesc>
	<MF_AutoTransferIntervalMultiplier>Auto transfer interval multiplier: {0}</MF_AutoTransferIntervalMultiplier>
	
	<MF_Settings_Work>Work</MF_Settings_Work>
	<MF_UsePrioritizedScanner>Use prioritized cross-level work scanner (Restart required)</MF_UsePrioritizedScanner>
	<MF_UsePrioritizedScannerTooltip>For cases when you have lots of potential low priority works on current map, but want pawns to do high-priority works on other levels first. Check Floors tab for more information.</MF_UsePrioritizedScannerTooltip>
	<MF_WorkGiverHighPriorityThresholdDesc>Works with higher or equal priority to this cutoff would be evaluated on all levels before low-priority works on pawns' current map.</MF_WorkGiverHighPriorityThresholdDesc>
	<MF_WorkGiverHighPriorityThreshold>Cross level work priority threshold: {0}</MF_WorkGiverHighPriorityThreshold>
	<MF_AddStayOnCurrentMapGizmo>Add a gizmo to restrict a pawn to always stay on current level. (Restart required)</MF_AddStayOnCurrentMapGizmo>
	<MF_UseExperimentalHauling>Experimental cross level hauling</MF_UseExperimentalHauling>
	<MF_UseExperimentalHaulingTooltip>Without using transfer settings or policies, pawns will automatically haul haulables not in stockpiles or in lower-priority stockpiles to a feasible one on other levels. Alternatively, you can turn this off and use transfer settings and policies to fully control the hauling.</MF_UseExperimentalHaulingTooltip>
	
	<MF_Settings_ResetToDefault>Reset to default</MF_Settings_ResetToDefault>
	
	
	<!-- stair utility -->
	<MF_GoToLevel>Go to: {0}</MF_GoToLevel>
	<MF_CurrentLevel>Current level: {0}</MF_CurrentLevel>
	<MF_PowerOutput>Power output on this level: {0}W</MF_PowerOutput>
	<MF_ViewConnectedLevel>View connected level</MF_ViewConnectedLevel>
	<MF_ViewConnectedLevelDesc>View connected level</MF_ViewConnectedLevelDesc>
	<MF_DeleteConnectedLevel>Delete connected levels</MF_DeleteConnectedLevel>
	<MF_DeleteConnectedLevelDesc>Delete connected levels</MF_DeleteConnectedLevelDesc>
	<MF_ConfirmDeleteConnectedLevel>[Dangerous!!!]Deleting the connected level will permanently remove everything on it and any levels branching from it. Are you sure you want to proceed?</MF_ConfirmDeleteConnectedLevel>
	<MF_AutoTransferToggle>Auto transfer</MF_AutoTransferToggle>
	<MF_AutoTransferToggleDesc>If enabled, the stair will periodically scan for permitted items (within the maximum range specified in the Transfer Policy) and add them to the load list. Pawns will haul them from current level to the connected level automatically.</MF_AutoTransferToggleDesc>
	<MF_LinkedElevatorLevel>Linked with: {0}</MF_LinkedElevatorLevel>
	<MF_BuildUpperElevator>Build on upper level</MF_BuildUpperElevator>
	<MF_BuildUpperElevatorDesc>Elevators must be built on the same cell to function. Place a blueprint on the upper level.</MF_BuildUpperElevatorDesc>
	<MF_BuildLowerElevator>Build on lower level</MF_BuildLowerElevator>
	<MF_BuildLowerElevatorDesc>Elevators must be built on the same cell to function. Place a blueprint on the lower level.</MF_BuildLowerElevatorDesc>
	<MF_LinkElevator>Link elevators</MF_LinkElevator>
	<MF_LinkElevatorDesc>Link all elevators on this cell so pawns can move between each other.</MF_LinkElevatorDesc>
	<MF_UnlinkingElevators>Unlinking elevators...</MF_UnlinkingElevators>
	<MF_PrintStairsToggle>Show stairs</MF_PrintStairsToggle>
	<MF_PrintStairsToggleDesc>Turn it off to make stairs invisible.</MF_PrintStairsToggleDesc>
	
	<MF_StairTransferTabLabel>Transfer</MF_StairTransferTabLabel>
	<MF_ExclusiveStairsStorageSettings>Exclusive</MF_ExclusiveStairsStorageSettings>
	<MF_ExclusiveStairsStorageSettingsTooltip>When toggled on, it will automatically disallow all currently allowed things on the connected stairs to prevent hauling back and forth.</MF_ExclusiveStairsStorageSettingsTooltip>
	<MF_StairTransferPolicyTabLabel>Policy</MF_StairTransferPolicyTabLabel>
	<MF_StairToLoadListTabLabel>To transfer</MF_StairToLoadListTabLabel>
	
	<!-- power transmit tab -->
	<MF_StairNotConnectedToPowerNet>Not connected to power net. Connect them with power conduit.</MF_StairNotConnectedToPowerNet>
	<MF_AllPowerNetNetOutput>Net power output in connected nets: {0}W</MF_AllPowerNetNetOutput>
	<MF_PowerTransmitted>Power transmitted from this node: {0}W</MF_PowerTransmitted>
	<MF_PowerBreakdown>Power Breakdown:</MF_PowerBreakdown>
	
	<!-- transfer policy tab -->
	<MF_TransferPolicyTabAllowedDefs>Allowed</MF_TransferPolicyTabAllowedDefs>
	<MF_TransferPolicyTabSearchDesc>Search def, click on them to add an entry in policy</MF_TransferPolicyTabSearchDesc>
	<MF_TransferPolicyTabEntryDesc>Adjust current policy</MF_TransferPolicyTabEntryDesc>
	<MF_TransferPolicyTabEntryTooltip>The stairs will periodically search for the allowed items in Transfer settings and automatically add them to the transfer list. You can prevent overloading or unnecessary transfers by setting a max amount here. If the resource counter on the target level shows that there are enough of an item, it won’t add that item to the transfer list anymore. Conversely, a negative setting will keep the appropriate number of items on current level and transfer the rest to the target level.</MF_TransferPolicyTabEntryTooltip>
	<MF_TransferPolicyCountEverything>Count everything</MF_TransferPolicyCountEverything>
	<MF_TransferPolicyCountEverythingTooltip>When toggle off, it only count items in the stockpile.</MF_TransferPolicyCountEverythingTooltip>
	<MF_MaxCountToTransfer>Max allowed:</MF_MaxCountToTransfer>
	
	<!-- stair place worker -->
	<MF_RoomTooSmall>Room size is too small. Must be at least {0} cells.</MF_RoomTooSmall>
	<MF_MustBeBuiltIndoor>Must be built indoor and under the roof.</MF_MustBeBuiltIndoor>
	<MF_CantBuildUpStairInBasement>Can't build upstairs in basement.</MF_CantBuildUpStairInBasement>
	<MF_CantBuildUpStairWithoutRoof>Can't build upstairs without roof.</MF_CantBuildUpStairWithoutRoof>
	<MF_CantBuildDownStairAboveGround>Can't build downstairs on upper levels.</MF_CantBuildDownStairAboveGround>
	<MF_CantBuildDownStairInCurrentBiome>Can't build downstairs in current biome.</MF_CantBuildDownStairInCurrentBiome>
	<MF_CantBuildInSameRoom>Can't build same kind of stair in the same room.</MF_CantBuildInSameRoom>
	<MF_PotentialElevatorToLink>Can be linked with:</MF_PotentialElevatorToLink>
	<MF_NoElevatorToLinkWith>No elevator can be linked.</MF_NoElevatorToLinkWith>
	
	<!-- haul across level designator -->
	<MF_DesignatorHaulTo>Haul to {0}</MF_DesignatorHaulTo>
	<MF_DesignatorHaulToDestMapLabel>Haul to </MF_DesignatorHaulToDestMapLabel>
	<MF_DesignatorHaulToDestMapDesc>Mark items to be hauled to a specific level.</MF_DesignatorHaulToDestMapDesc>
	<MF_MustSelectTargetViaRightClickFirst>Must select destination through right click options first.</MF_MustSelectTargetViaRightClickFirst>
	
	<!-- float menu options -->
	<MF_TransferEntityTo>Transfer {1_label} to {2}</MF_TransferEntityTo>
	<MF_RescueTo>Rescue {1_labelShort} to ...</MF_RescueTo>
	<MF_ReturnToSlaveBed>Return slave {1_labelShort} to ...</MF_ReturnToSlaveBed>
	<MF_CaptureTo>Capture {1_labelShort} to ...</MF_CaptureTo>
	<MF_ArrestTo>Arrest {1_labelShort} to ...</MF_ArrestTo>
	<MF_RescueToLevel>Rescue {1_labelShort} to {2}</MF_RescueToLevel>
	<MF_ReturnToSlaveBedOnLevel>Return slave {1_labelShort} to {2}</MF_ReturnToSlaveBedOnLevel>
	<MF_CaptureToLevel>Capture {1_labelShort} to {2}</MF_CaptureToLevel>
	<MF_ArrestToLevel>Arrest {1_labelShort} to {2}</MF_ArrestToLevel>
	<MF_BedOwners>Owners: {0}</MF_BedOwners>
	<MF_BedNoOwners>No owner</MF_BedNoOwners>
	<MF_NoAppropriateBedOnCurrentLevel>No appropriate bed on this level.</MF_NoAppropriateBedOnCurrentLevel>

	<MF_StayOnCurrentMapToggle>Stay here</MF_StayOnCurrentMapToggle>
	<MF_StayOnCurrentMapToggleDesc>Pawns wouldn't search for jobs or switch to other levels when toggle on.</MF_StayOnCurrentMapToggleDesc>
	
	<MF_ListenBillGiver>Link with other level</MF_ListenBillGiver>
	<MF_ListenBillGiverTooltip>Pawns won’t automatically haul missing ingredients across levels. However, when toggled on, the workbench will automatically scan for missing ingredients on the linked level and add them to the haul queue. The performance impact depends on how many types are allowed in the bill filter, so try to keep it as minimal as possible. Turn if off if you have a dedicated stockpile on this level and it would do nothing.</MF_ListenBillGiverTooltip>
	<MF_BillGiverLinkedMap>Link with level</MF_BillGiverLinkedMap>
	<MF_BillGiverLinkedMapTooltip>Link with other level so pawns could haul missing ingredients from there.</MF_BillGiverLinkedMapTooltip>
	
	<MF_GatherPawnsCommand>Gather</MF_GatherPawnsCommand>
	<MF_GatherPawnsCommandDesc>Call colonists to move to the current spot.</MF_GatherPawnsCommandDesc>
	<MF_GatherPawnsSelected>Selected:</MF_GatherPawnsSelected>
	<MF_GatherPawnsAllCandidates>Candidates:</MF_GatherPawnsAllCandidates>
	<MF_GatherPawns_CancelButtonLabel>Cancel</MF_GatherPawns_CancelButtonLabel>
	<MF_GatherPawns_AcceptButtonLabel>Gather</MF_GatherPawns_AcceptButtonLabel>
	<MF_GatherPawns_AddAllButtonLabel>Select/Deselect All</MF_GatherPawns_AddAllButtonLabel>
    <MF_GatherPawns_AddPrevSelectedButtonLabel>Select/Deselect Prev.</MF_GatherPawns_AddPrevSelectedButtonLabel>
	
	<MF_NotUsableOnUpperLevels>Not usable on upper levels.</MF_NotUsableOnUpperLevels>
	
	<!-- pipe connector Rimefeller and VEF -->
	<MF_PipeConnectorLinkedWith>Linked with: {0}</MF_PipeConnectorLinkedWith>
	<MF_BuildUpperPipeConnector>Build upper</MF_BuildUpperPipeConnector>
	<MF_BuildUpperPipeConnectorDesc>Place a blueprint of a pipe connector on the upper level.</MF_BuildUpperPipeConnectorDesc>
	<MF_LinkUpperPipeConnector>Link upper</MF_LinkUpperPipeConnector>
	<MF_LinkUpperPipeConnectorDesc>Link current connector with the one on the upper level. So they can transmit resources between each other.</MF_LinkUpperPipeConnectorDesc>
	<MF_BuildLowerPipeConnector>Build lower</MF_BuildLowerPipeConnector>
	<MF_BuildLowerPipeConnectorDesc>Place a blueprint of a pipe connector on the lower level.</MF_BuildLowerPipeConnectorDesc>
	<MF_LinkLowerPipeConnector>Link lower</MF_LinkLowerPipeConnector>
	<MF_LinkLowerPipeConnectorDesc>Link current connector with the one on the lower level. So they can transmit resources between each other.</MF_LinkLowerPipeConnectorDesc>
	<MF_CannotFindPipeConnectorToLink>No pipe connector to link.</MF_CannotFindPipeConnectorToLink>
	<MF_PipeConnectorExporting>Exporting</MF_PipeConnectorExporting>
	<MF_PipeConnectorExportingDesc>If toggle, the connector will transmit resources to linked connector on other level. Otherwise, it receive resources from others.</MF_PipeConnectorExportingDesc>
	<MF_StopPipeConnector>Stop</MF_StopPipeConnector>
	<MF_StopPipeConnectorDesc>Stop transmission.</MF_StopPipeConnectorDesc>
	
	<!-- VEF pipe system, what a mess -->
	<MF_SetPipeNetDef>Set resource to transmit</MF_SetPipeNetDef>
	<MF_SetPipeNetDefDesc>Select which resource the connector should transmit.</MF_SetPipeNetDefDesc>
	<MF_SetPipeNetDefTo>Resource set to {0}.</MF_SetPipeNetDefTo>
	<MF_ConnectedToPipeNetWithDef>Connected to pipe net of {0}.</MF_ConnectedToPipeNetWithDef>
	<MF_CannotFindPipeNetWithDef>Cannot find nearby pipe net of {0}.</MF_CannotFindPipeNetWithDef>
	<MF_ReconnectToPipeNet>Reconnect</MF_ReconnectToPipeNet>
	<MF_ReconnectToPipeNetDesc>Reconnect to a nearby pipe net after you modify it.</MF_ReconnectToPipeNetDesc>
	<MF_NoPipeNetDef>Not working: set resource first.</MF_NoPipeNetDef>
	<MF_CurrentPipeNetDef>Current resource: {0}</MF_CurrentPipeNetDef>
	<MF_NotConnectedToPipeNet>Not working: not connected to any pipe net.</MF_NotConnectedToPipeNet>
	<MF_ConnectedToEmptyPipeNet>Not working: exporter connected to an empty pipe net. Please reconnect it to a pipe net of {0} with containers.</MF_ConnectedToEmptyPipeNet>
	<MF_NotLinkedWithPipeConnector>Not working: link with another pipe connector first.</MF_NotLinkedWithPipeConnector>
	<MF_LinkedPipeConnectorNotConnectedToPipeNet>Not working: linked pipe connector not connected to pipe net.</MF_LinkedPipeConnectorNotConnectedToPipeNet>
	<MF_ExporterPipeNetStorage>Resource available in exporter net: {0}</MF_ExporterPipeNetStorage>
	<MF_NoContainerInReceiverNet>Not working: no container in receiver pipe net.</MF_NoContainerInReceiverNet>
	<MF_ReceiverNetCapacity>Capacity of receiver net: {0}</MF_ReceiverNetCapacity>
	<MF_PipeConnectorSetFlowRate>Set flow rate to {0} (every 250 ticks)</MF_PipeConnectorSetFlowRate>
	<MF_SetFlowRate>Rate</MF_SetFlowRate>
	<MF_SetFlowRateDesc>Configure the transmission speed.</MF_SetFlowRateDesc>
	<MF_PipeConnectorFlowRate>Flow rate: {0}</MF_PipeConnectorFlowRate>
	
	<!-- pawn columns -->
	<MF_HighPriorityWorkGiverTypes>Following works would be scanned on pawn's current level, then other levels\n</MF_HighPriorityWorkGiverTypes>
	<MF_LowPriorityWorkGiverTypes>If not found, following works would be scanned on pawn's current level, then other levels\n</MF_LowPriorityWorkGiverTypes>

	<!-- elevator - transfer vehicle -->
	<MF_TransferVehicle>Transfer vehicle</MF_TransferVehicle>
	<MF_TransferVehicleDesc>Transfer vehicle between levels.</MF_TransferVehicleDesc>
	<MF_NoVehicleNearby>No vehicle nearby, drive closer.</MF_NoVehicleNearby>
	<MF_TransferVehicleTo>Transfer {0} to {1}</MF_TransferVehicleTo>

</LanguageData>